Markov.py
Markov-0.4.0.dist-info/DESCRIPTION.rst
Markov-0.4.0.dist-info/METADATA
Markov-0.4.0.dist-info/RECORD
Markov-0.4.0.dist-info/WHEEL
Markov-0.4.0.dist-info/metadata.json
Markov-0.4.0.dist-info/top_level.txt
