Metadata-Version: 2.0
Name: Markov
Version: 0.4.0
Summary: Python library for Hidden Markov Models
Home-page: https://sourceforge.net/projects/python-hidden-markov/
Author: Dr Peter J Bleackley
Author-email: peter.bleackley@playfultechnology.co.uk
License: UNKNOWN
Download-URL: https://drive.google.com/#folders/0B68FS-e9xvMYYlhaNnluLXpFRlE
Platform: UNKNOWN
Classifier: Programming Language :: Python
Classifier: Programming Language :: Python :: 2.7
Classifier: Programming Language :: Python :: 3.7
Classifier: Development Status :: 3 - Alpha
Classifier: Environment :: Other Environment
Classifier: Intended Audience :: Science/Research
Classifier: Intended Audience :: Information Technology
Classifier: Intended Audience :: Developers
Classifier: License :: OSI Approved :: Mozilla Public License 1.1 (MPL 1.1)
Classifier: Operating System :: OS Independent
Classifier: Topic :: Scientific/Engineering :: Artificial Intelligence
Classifier: Topic :: Software Development :: Libraries
Classifier: Topic :: Software Development :: Libraries :: Python Modules
